Metadata-Version: 1.0
Name: shinkenplugins.plugins.nova-host-status
Version: 1.0
Summary: check the current status for a nova host
Home-page: https://github.com/savoirfairelinux/sfl-shinken-plugins
Author: Flavien Peyre
Author-email: peyre.flavien@gmail.com
License: GPL3+
Platform: any
